NodeDefender/__init__.py
NodeDefender/cli.py
NodeDefender/decorators.py
NodeDefender/factory.py
NodeDefender/security.py
NodeDefender/auth/register.py
NodeDefender/config/__init__.py
NodeDefender/config/__init__.pyc
NodeDefender/config/celery.py
NodeDefender/config/celery.pyc
NodeDefender/config/database.py
NodeDefender/config/database.pyc
NodeDefender/config/factory.py
NodeDefender/config/general.py
NodeDefender/config/general.pyc
NodeDefender/config/logging.py
NodeDefender/config/logging.pyc
NodeDefender/config/mail.py
NodeDefender/config/mail.pyc
NodeDefender/config/redis.py
NodeDefender/config/redis.pyc
NodeDefender/config/__pycache__/__init__.cpython-34.pyc
NodeDefender/config/__pycache__/celery.cpython-34.pyc
NodeDefender/config/__pycache__/database.cpython-34.pyc
NodeDefender/config/__pycache__/factory.cpython-34.pyc
NodeDefender/config/__pycache__/general.cpython-34.pyc
NodeDefender/config/__pycache__/logging.cpython-34.pyc
NodeDefender/config/__pycache__/mail.cpython-34.pyc
NodeDefender/config/__pycache__/redis.cpython-34.pyc
NodeDefender/db/__init__.py
NodeDefender/db/commandclass.py
NodeDefender/db/field.py
NodeDefender/db/group.py
NodeDefender/db/icpe.py
NodeDefender/db/message.py
NodeDefender/db/mqtt.py
NodeDefender/db/node.py
NodeDefender/db/sensor.py
NodeDefender/db/user.py
NodeDefender/db/__pycache__/__init__.cpython-34.pyc
NodeDefender/db/__pycache__/commandclass.cpython-34.pyc
NodeDefender/db/__pycache__/field.cpython-34.pyc
NodeDefender/db/__pycache__/group.cpython-34.pyc
NodeDefender/db/__pycache__/icpe.cpython-34.pyc
NodeDefender/db/__pycache__/message.cpython-34.pyc
NodeDefender/db/__pycache__/mqtt.cpython-34.pyc
NodeDefender/db/__pycache__/node.cpython-34.pyc
NodeDefender/db/__pycache__/sensor.cpython-34.pyc
NodeDefender/db/__pycache__/user.cpython-34.pyc
NodeDefender/db/data/__init__.py
NodeDefender/db/data/event.py
NodeDefender/db/data/heat.py
NodeDefender/db/data/power.py
NodeDefender-0.8.12.dist-info/METADATA
NodeDefender-0.8.12.dist-info/RECORD
NodeDefender-0.8.12.dist-info/WHEEL
NodeDefender-0.8.12.dist-info/entry_points.txt
NodeDefender-0.8.12.dist-info/top_level.txt
