Metadata-Version: 2.1
Name: NodeDefender
Version: 0.8.12
Summary: Manage Nodes with CTS-iCPE
Home-page: https://github.com/CTSNE/NodeDefender
Author: Henrik Nilsson
Author-email: henrik.nilsson@ctsystem.se
License: BSD
Platform: UNKNOWN
Requires-Dist: alembic (==0.9.8)
Requires-Dist: amqp (==2.2.2)
Requires-Dist: aniso8601 (==3.0.0)
Requires-Dist: APScheduler (==3.5.1)
Requires-Dist: bcrypt (==3.1.4)
Requires-Dist: billiard (==3.5.0.3)
Requires-Dist: celery (==4.1.0)
Requires-Dist: certifi (==2018.1.18)
Requires-Dist: cffi (==1.11.5)
Requires-Dist: chardet (==3.0.4)
Requires-Dist: click (==6.7)
Requires-Dist: Flask (==0.12.2)
Requires-Dist: Flask-Bcrypt (==0.7.1)
Requires-Dist: Flask-Login (==0.4.1)
Requires-Dist: Flask-Migrate (==2.1.1)
Requires-Dist: Flask-Moment (==0.6.0)
Requires-Dist: Flask-RESTful (==0.3.6)
Requires-Dist: Flask-Script (==2.0.6)
Requires-Dist: Flask-SocketIO (==2.9.6)
Requires-Dist: Flask-SQLAlchemy (==2.3.2)
Requires-Dist: Flask-WTF (==0.14.2)
Requires-Dist: geopy (==1.12.0)
Requires-Dist: gevent (==1.2.2)
Requires-Dist: greenlet (==0.4.13)
Requires-Dist: idna (==2.6)
Requires-Dist: itsdangerous (==0.24)
Requires-Dist: Jinja2 (==2.10)
Requires-Dist: kombu (==4.1.0)
Requires-Dist: Mako (==1.0.7)
Requires-Dist: MarkupSafe (==1.0)
Requires-Dist: paho-mqtt (==1.3.1)
Requires-Dist: pycparser (==2.18)
Requires-Dist: PyMySQL (==0.8.0)
Requires-Dist: python-dateutil (==2.7.0)
Requires-Dist: python-editor (==1.0.3)
Requires-Dist: python-engineio (==2.0.4)
Requires-Dist: python-socketio (==1.9.0)
Requires-Dist: pytz (==2018.3)
Requires-Dist: redis (==2.10.6)
Requires-Dist: redlock (==1.2.0)
Requires-Dist: requests (==2.18.4)
Requires-Dist: six (==1.11.0)
Requires-Dist: SQLAlchemy (==1.2.5)
Requires-Dist: tzlocal (==1.5.1)
Requires-Dist: urllib3 (==1.22)
Requires-Dist: vine (==1.1.4)
Requires-Dist: Werkzeug (==0.14.1)
Requires-Dist: WTForms (==2.1)
